Workbook

Sheet Hypotheses
A1: HYPOTHESES FINANCIERES — NEXUS
A2: Modifiez ces valeurs pour voir l'impact sur tous les onglets
A4: Parametre | B4: Valeur | C4: Note
A5: Prix Free (EUR/mois) | B5: 0 | C5: Gratuit a vie
A6: Prix Basic (EUR/mois) | B6: 29 | C6: Illimite + 1000 credits IA/mois
A7: Prix Business (EUR/mois) | B7: 149 | C7: Multi-site + 10000 credits IA/mois
A8: Mix Free (%) | B8: 0.1 | C8: Utilisateurs gratuits
A9: Mix Basic (%) | B9: 0.7 | C9: Coeur de cible PME
A10: Mix Business (%) | B10: 0.2 | C10: Multi-sites, franchises
A11: ARPA (revenu moyen/client/mois) | B11: =B5*B8+B6*B9+B7*B10 | C11: =B5*B8+B6*B9+B7*B10
A13: Churn mensuel An 1 | B13: 0.03 | C13: Benchmark SaaS SMB
A14: Churn mensuel An 2 | B14: 0.025 | C14: Amelioration onboarding
A15: Churn mensuel An 3 | B15: 0.02 | C15: Produit mature
A17: Cout infra fixe (EUR/mois) | B17: 150 | C17: Render + Supabase base
A18: Cout variable/client (EUR/mois) | B18: 5 | C18: Anthropic + Twilio + Resend
A19: Commission Stripe (%) | B19: 0.029 | C19: 2.9%
A21: Salaire fondateur M1-M6 | B21: 0 | C21: Pas de salaire les 6 premiers mois
A22: Salaire fondateur M7+ An 1 (EUR/mois) | B22: 1200 | C22: Phase demarrage
A23: Salaire fondateur An 2 (EUR/mois) | B23: 2000 | C23: Croissance
A24: Salaire fondateur An 3 (EUR/mois) | B24: 3000 | C24: Rentabilite
A25: Taux charges sociales | B25: 0.45 | C25: SASU regime general
A27: Comptable / juridique | B27: 0 | C27: Fondateur = comptable (BEP + 10 ans exp)
... A34: IS taux normal | B34: 0.25 | C34: Au-dela de 42500 EUR

Sheet Plan Financement
A1: PLAN DE FINANCEMENT INITIAL — 40 000 EUR (+ NACRE 5K optionnel)
A3: BESOINS | D3: RESSOURCES
A4: Poste | B4: Montant | D4: Poste | E4: Montant
A5: Fonds de roulement (6 mois charges mini) | B5: 18000 | D5: Capital social SASU | E5: 1
A6: Tresorerie de securite (couverture pertes Y1) | B6: 16000 | D6: Apport en nature (logiciel NEXUS v3.25) | E6: 80000
A7: Marketing lancement (reseaux, pub ciblee) | B7: 3000 | D7: Pret d'honneur Initiative 95 | E7: 15000
A8: Materiel informatique | B8: 1500 | D8: Pret bancaire (garanti BPI 60%) | E8: 25000
A9: Frais d'etablissement (SASU, juridique) | B9: 1500 | D9: NACRE phase 2 (OPTIONNEL) | E9: 5000
A11: TOTAL BESOINS | B11: =SUM(B5:B9) | D11: TOTAL TRESORERIE BASE (sans NACRE) | E11: =E7+E8
A13: Equilibre (Ressources tresorerie - Besoins) | B13: =E11-B11 | D13: TOTAL AVEC NACRE (optionnel) | E13: =E7+E8+E9
A15: Note : L'apport en nature (80 000 EUR) valorise le logiciel developpe
A16: pendant 18 mois. Il n'apporte pas de tresorerie mais renforce les fonds propres.
A17: NACRE = gere par la Region (pas France Travail). Bonus si eligible, pas indispensable.

Sheet Clients & MRR
A1: EVOLUTION CLIENTS ET MRR — ANNEE 1
A2: Les colonnes Nouveaux et Churn sont modifiables. Le reste se recalcule.
A4: Mois | B4: Nouveaux | C4: Churn | D4: Clients fin mois | E4: MRR (EUR) | F4: ARR annualise
A5: M1 | B5: 6 | C5: 0 | D5: =B5-C5 | E5: =D5*Hypotheses!B11 | F5: =E5*12
A6: M2 | B6: 7 | C6: 0 | D6: =D5+B6-C6 | E6: =D6*Hypotheses!B11 | F6: =E6*12
A7: M3 | B7: 8 | C7: 0 | D7: =D6+B7-C7 | E7: =D7*Hypotheses!B11 | F7: =E7*12
A8: M4 | B8: 9 | C8: 1 | D8: =D7+B8-C8 | E8: =D8*Hypotheses!B11 | F8: =E8*12
A9: M5 | B9: 10 | C9: 1 | D9: =D8+B9-C9 | E9: =D9*Hypotheses!B11 | F9: =E9*12
A10: M6 | B10: 10 | C10: 1 | D10: =D9+B10-C10 | E10: =D10*Hypotheses!B11 | F10: =E10*12
A11: M7 | B11: 11 | C11: 1 | D11: =D10+B11-C11 | E11: =D11*Hypotheses!B11 | F11: =E11*12
A12: M8 | B12: 12 | C12: 2 | D12: =D11+B12-C12 | E12: =D12*Hypotheses!B11 | F12: =E12*12
A13: M9 | B13: 12 | C13: 2 | D13: =D12+B13-C13 | E13: =D13*Hypotheses!B11 | F13: =E13*12
A14: M10 | B14: 13 | C14: 2 | D14: =D13+B14-C14 | E14: =D14*Hypotheses!B11 | F14: =E14*12
A15: M11 | B15: 14 | C15: 3 | D15: =D14+B15-C15 | E15: =D15*Hypotheses!B11 | F15: =E15*12
A16: M12 | B16: 14 | C16: 3 | D16: =D15+B16-C16 | E16: =D16*Hypotheses!B11 | F16: =E16*12
A17: Total An 1 | B17: =SUM(B5:B16) | C17: =SUM(C5:C16) | D17: =D16 | E17: =E16 | F17: =F16
A19: An 2 (previsions)
A20: Nouveaux clients | B20: 278
A21: Churn total | B21: 63
A22: Clients fin An 2 | B22: =D17+B20-C21
A23: MRR fin An 2 | B23: =B22*Hypotheses!B11
A25: An 3 (previsions)
A26: Nouveaux clients | B26: 285
A27: Churn total | B27: 60
A28: Clients fin An 3 | B28: =B22+B26-C27
A29: MRR fin An 3 | B29: =B28*Hypotheses!B11

Sheet Compte Resultat
A1: COMPTE DE RESULTAT PREVISIONNEL (3 ANS)
A2: Lie aux onglets Hypotheses et Clients & MRR — Solo founder An 1/An 2, 1er recrutement An 3
A4: Poste | B4: An 1 | C4: An 2 | D4: An 3
A6: PRODUITS D'EXPLOITATION
A7: Abonnements SaaS + credits IA (HT) | B7: 35860 | C7: 149710 | D7: 309700
A8: Setup / accompagnement | B8: 6000 | C8: 13500 | D8: 16000
A9: TOTAL CA HT | B9: =B7+B8 | C9: =C7+C8 | D9: =D7+D8
A11: CHARGES VARIABLES
A12: Hebergement cloud (Render, Supabase) | B12: 2400 | C12: 4800 | D12: 8400
A13: Services tiers (Anthropic, Twilio, Resend) | B13: 3200 | C13: 12000 | D13: 24000
A14: Commissions Stripe (2.9%) | B14: 1200 | C14: 4700 | D14: 9500
A15: Total charges variables | B15: =SUM(B12:B14) | C15: =SUM(C12:C14) | D15: =SUM(D12:D14)
A17: MARGE BRUTE | B17: =B9-B15 | C17: =C9-C15 | D17: =D9-D15
A18: Taux de marge brute | B18: =B17/B9 | C18: =C17/C9 | D18: =D17/D9
A20: CHARGES FIXES
A21: Remuneration fondateur (net) | B21: 7200 | C21: 24000 | D21: 36000
A22: Charges sociales (45%) | B22: =B21*Hypotheses!B25 | C22: =C21*Hypotheses!B25 | D22: =D21*Hypotheses!B25
A23: Prestataires externes (missions) | B23: 0 | C23: 10000 | D23: 6000
A24: Salaire support/CSM (a partir M25) | B24: 0 | C24: 0 | D24: 24000
A25: Charges sociales CSM | B25: 0 | C25: 0 | D25: =D24*Hypotheses!B25
A26: Marketing & acquisition | B26: 3600 | C26: 9600 | D26: 14400
A27: Assurances (RC Pro) | B27: 1000 | C27: 1200 | D27: 2000
A28: Comptable / juridique (fondateur = comptable) | B28: 0 | C28: 0 | D28: 0
A29: Materiel / licences | B29: 500 | C29: 1500 | D29: 2500
A30: Loyer / coworking (domicile) | B30: 0 | C30: 0 | D30: 0
A31: Divers / imprevus | B31: 1200 | C31: 2000 | D31: 3000
A32: Total charges fixes | B32: =SUM(B21:B31) | C32: =SUM(C21:C31) | D32: =SUM(D21:D31)
A34: RESULTAT D'EXPLOITATION | B34: =B17-B32 | C34: =C17-C32 | D34: =D17-D32
A35: Charges financieres (interets emprunts) | B35: 375 | C35: 625 | D35: 500
A36: RESULTAT COURANT | B36: =B34-B35 | C36: =C34-C35 | D36: =D34-D35
A37: IS (15%/25%) | B37: =IF(B36<=0,0,IF(B36<=42500,B36*Hypotheses!B33,42500*Hypotheses!B33+(B36-42500)*Hypotheses!B34)) | C37: =IF(C36<=0,0,IF(C36<=42500,C36*Hypotheses!B33,42500*Hypotheses!B33+(C36-42500)*Hypotheses!B34)) | D37: =IF(D36<=0,0,IF(D36<=42500,D36*Hypotheses!B33,42500*Hypotheses!B33+(D36-42500)*Hypotheses!B34))
A38: RESULTAT NET | B38: =B36-B37 | C38: =C36-C37 | D38: =D36-D37
A40: CAF (Resultat + amortissements) | B40: =B38+1500 | C40: =C38+1500 | D40: =D38+1500

Sheet Tresorerie M1-M12
A1: PLAN DE TRESORERIE MENSUEL — ANNEE 1 (base 40K, sans NACRE)
B3: M1 | C3: M2 | D3: M3 | E3: M4 | F3: M5 | G3: M6 | H3: M7 | I3: M8 | J3: M9 | K3: M10 | L3: M11 | M3: M12 | N3: TOTAL
A4: ENCAISSEMENTS
A5: CA TTC (MRR x 1.2) | B5: ='Clients & MRR'!E5*(1+Hypotheses!B32) | C5: ='Clients & MRR'!E6*(1+Hypotheses!B32) | D5: ='Clients & MRR'!E7*(1+Hypotheses!B32) | E5: ='Clients & MRR'!E8*(1+Hypotheses!B32) | F5: ='Clients & MRR'!E9*(1+Hypotheses!B32) | G5: ='Clients & MRR'!E10*(1+Hypotheses!B32) | H5: ='Clients & MRR'!E11*(1+Hypotheses!B32) | I5: ='Clients & MRR'!E12*(1+Hypotheses!B32) | J5: ='Clients & MRR'!E13*(1+Hypotheses!B32) | K5: ='Clients & MRR'!E14*(1+Hypotheses!B32) | L5: ='Clients & MRR'!E15*(1+Hypotheses!B32) | M5: ='Clients & MRR'!E16*(1+Hypotheses!B32) | N5: =SUM(B5:M5)
A6: Pret honneur Initiative 95 | B6: 15000 | N6: =SUM(B6:M6)
A7: Pret bancaire (garanti BPI) | D7: 25000 | N7: =SUM(B7:M7)
A8: NACRE phase 2 (OPTIONNEL) | N8: 0
A9: TOTAL ENCAISSEMENTS | B9: =SUM(B5:B8) | C9: =SUM(C5:C8) | D9: =SUM(D5:D8) | E9: =SUM(E5:E8) | F9: =SUM(F5:F8) | G9: =SUM(G5:G8) | H9: =SUM(H5:H8) | I9: =SUM(I5:I8) | ... N9: =SUM(N5:N8)
A11: DECAISSEMENTS
A12: Hebergement cloud | B12: 150 | C12: 150 | D12: 175 | E12: 175 | F12: 200 | G12: 200 | H12: 200 | I12: 200 | J12: 225 | K12: 225 | L12: 250 | M12: 250 | N12: =SUM(B12:M12)
A13: Services tiers (Anthropic/Twilio/Resend) | B13: 150 | C13: 175 | D13: 200 | E13: 225 | F13: 250 | G13: 275 | H13: 300 | I13: 325 | J13: 350 | K13: 375 | L13: 375 | M13: 400 | N13: =SUM(B13:M13)
A14: Commissions Stripe | B14: 22 | C14: 37 | D14: 54 | E14: 70 | F14: 89 | G14: 107 | H14: 128 | I14: 148 | J14: 167 | K14: 190 | L14: 213 | M14: 234 | N14: =SUM(B14:M14)
A15: Salaire fondateur net (M7-M12) | B15: 0 | C15: 0 | D15: 0 | E15: 0 | F15: 0 | G15: 0 | H15: 1200 | I15: 1200 | J15: 1200 | K15: 1200 | L15: 1200 | M15: 1200 | N15: =SUM(B15:M15)
A16: Charges sociales fondateur | B16: 0 | C16: 0 | D16: 0 | E16: 0 | F16: 0 | G16: 0 | H16: 540 | I16: 540 | J16: 540 | K16: 540 | L16: 540 | M16: 540 | N16: =SUM(B16:M16)
A17: Marketing | B17: 300 | C17: 300 | D17: 300 | E17: 300 | F17: 300 | G17: 300 | H17: 300 | I17: 300 | J17: 300 | K17: 300 | L17: 300 | M17: 300 | N17: =SUM(B17:M17)
A18: Assurances (RC Pro) | B18: 83 | C18: 83 | D18: 83 | E18: 83 | F18: 83 | G18: 83 | H18: 83 | I18: 83 | J18: 83 | K18: 83 | L18: 83 | M18: 83 | N18: =SUM(B18:M18)
A19: Materiel | B19: 500 | C19: 0 | D19: 0 | E19: 0 | F19: 0 | G19: 0 | H19: 0 | I19: 0 | J19: 0 | K19: 0 | L19: 0 | M19: 0 | N19: =SUM(B19:M19)
A20: Remboursement emprunts | B20: 0 | C20: 0 | D20: 0 | E20: 0 | F20: 0 | G20: 0 | H20: 728 | I20: 728 | J20: 728 | K20: 728 | L20: 728 | M20: 728 | N20: =SUM(B20:M20)
A21: TVA a reverser | B21: 0 | C21: 0 | D21: 0 | E21: 0 | F21: 0 | G21: 0 | H21: 0 | I21: 0 | J21: 800 | K21: 0 | L21: 0 | M21: 1600 | N21: =SUM(B21:M21)
A22: Divers / imprevus | B22: 100 | C22: 100 | D22: 100 | E22: 100 | F22: 100 | G22: 100 | H22: 100 | I22: 100 | J22: 100 | K22: 100 | L22: 100 | M22: 100 | N22: =SUM(B22:M22)
A23: TOTAL DECAISSEMENTS | B23: =SUM(B12:B22) | C23: =SUM(C12:C22) | D23: =SUM(D12:D22) | E23: =SUM(E12:E22) | F23: =SUM(F12:F22) | G23: =SUM(G12:G22) | H23: =SUM(H12:H22) | I23: =SUM(I12:I22) | ... N23: =SUM(N12:N22)
A25: SOLDE DU MOIS | B25: =B9-B23 | C25: =C9-C23 | D25: =D9-D23 | E25: =E9-E23 | F25: =F9-F23 | G25: =G9-G23 | H25: =H9-H23 | I25: =I9-I23 | ... N25: =N9-N23
A26: TRESORERIE CUMULEE | B26: =B25 | C26: =B26+C25 | D26: =C26+D25 | E26: =D26+E25 | F26: =E26+F25 | G26: =F26+G25 | H26: =G26+H25 | I26: =H26+I25 | J26: =I26+J25 | ... M26: =L26+M25

Sheet Seuil Rentabilite
A1: SEUIL DE RENTABILITE
A2: Seuil atteint a ~50 clients (M6-M7, fin S1)
B3: An 1 | C3: An 2 | D3: An 3
A4: Charges fixes totales | B4: ='Compte Resultat'!B32 | C4: ='Compte Resultat'!C32 | D4: ='Compte Resultat'!D32
A5: Taux de marge sur couts variables | B5: ='Compte Resultat'!B18 | C5: ='Compte Resultat'!C18 | D5: ='Compte Resultat'!D18
A6: SEUIL DE RENTABILITE (CA HT) | B6: =B4/B5 | C6: =C4/C5 | D6: =D4/D5
A7: Seuil mensuel | B7: =B6/12 | C7: =C6/12 | D7: =D6/12
A8: Nb clients equivalent (ARPA) | B8: =B7/Hypotheses!B11 | C8: =C7/Hypotheses!B11 | D8: =D7/Hypotheses!B11
A10: CA previsionnel | B10: ='Compte Resultat'!B9 | C10: ='Compte Resultat'!C9 | D10: ='Compte Resultat'!D9
A11: Marge de securite (CA - Seuil) | B11: =B10-B6 | C11: =C10-C6 | D11: =D10-D6
A12: Taux de marge de securite | B12: =B11/B10 | C12: =C11/C10 | D12: =D11/D10

Sheet Bilan
A1: BILAN PREVISIONNEL
A3: ACTIF | B3: An 1 | C3: An 2 | D3: An 3 | E3: PASSIF | F3: An 1 | G3: An 2 | H3: An 3
A4: Immobilisations incorporelles (net) | B4: 13500 | C4: 12000 | D4: 10500 | E4: Capital social (SASU) | F4: 1 | G4: 1 | H4: 1
A5: Immobilisations corporelles (net) | B5: 1000 | C5: 500 | D5: 0 | E5: Reserves | F5: 0 | G5: ='Compte Resultat'!B38 | H5: =F5+'Compte Resultat'!C38
A6: Creances clients | B6: 0 | C6: 0 | D6: 0 | E6: Resultat de l'exercice | F6: ='Compte Resultat'!B38 | G6: ='Compte Resultat'!C38 | H6: ='Compte Resultat'!D38
A7: Tresorerie | B7: ='Tresorerie M1-M12'!M26 | C7: 120000 | D7: 240000 | E7: Emprunts LT | F7: 35632 | G7: 25780 | H7: 15928
A8: TOTAL ACTIF | B8: =SUM(B4:B7) | C8: =SUM(C4:C7) | D8: =SUM(D4:D7) | E8: Dettes courantes | F8: 9651 | G8: 13727 | H8: 14396
E11: TOTAL PASSIF | F11: =SUM(F4:F10) | G11: =SUM(G4:G10) | H11: =SUM(H4:H10)
A13: Verification Actif = Passif | E13: Ecart | F13: =B8-F11 | G13: =C8-G11 | H13: =D8-H11

Sheet Scenario Pessimiste
A1: SCENARIO PESSIMISTE (-30% acquisition)
A2: Hypothese : 30% de clients en moins, charges ajustees a la baisse
B4: An 1 | C4: An 2 | D4: An 3
A5: Facteur reduction acquisition | B5: 0.7 | C5: Modifiez cette cellule pour ajuster le scenario
A7: Clients fin annee | B7: =ROUND('Clients & MRR'!D17*$B$5,0) | C7: =ROUND('Clients & MRR'!B22*$B$5,0) | D7: =ROUND('Clients & MRR'!B28*$B$5,0)
A8: MRR fin annee | B8: =B7*Hypotheses!B11 | C8: =C7*Hypotheses!B11 | D8: =D7*Hypotheses!B11
A9: CA HT (pessimiste) | B9: ='Compte Resultat'!B9*$B$5 | C9: ='Compte Resultat'!C9*$B$5 | D9: ='Compte Resultat'!D9*$B$5
A10: Charges totales (ajustees) | B10: 20100 | C10: 62600 | D10: 120800
A11: Resultat net (pessimiste) | B11: =B9-B10 | C11: =C9-C10 | D11: =D9-D10
A13: Tresorerie fin annee | B13: 47200 | C13: =B13+C11 | D13: =C13+D11
A15: Actions correctives si scenario pessimiste :
A16: → Reduction marketing de 50%
A17: → Reduction salaire fondateur temporairement
A18: → Negociation report echeance prets d'honneur
A19: → Missions freelance en parallele pour le fondateur
A20: → Tresorerie reste POSITIVE meme a -30% (modele frugal)

Sheet Remboursements
A1: ECHEANCIER DES REMBOURSEMENTS
A3: Type | B3: Capital | C3: Taux | D3: Duree | E3: Differe | F3: Mensualite | G3: Debut remb.
A4: Pret honneur Initiative 95 | B4: 15000 | C4: 0% | D4: 5 ans | E4: 6 mois | F4: =B4/54 | G4: M7
A5: Pret bancaire (garanti BPI 60%) | B5: 25000 | C5: 3% | D5: 5 ans | E5: 6 mois | F5: 450 | G5: M7
A6: NACRE phase 2 (beneficiaire ASS) | B6: 5000 | C6: 0% | D6: 5 ans | E6: 12 mois | F6: =B6/48 | G6: M13
A7: TOTAL | B7: =SUM(B4:B6)
A9: ECHEANCIER ANNUEL
B10: An 1 | C10: An 2 | D10: An 3 | E10: Total
A11: Remb. pret I95 | B11: =F4*6 | C11: =F4*12 | D11: =F4*12 | E11: =SUM(B11:D11)
A12: Remb. pret bancaire | B12: =6*450 | C12: =12*450 | D12: =12*450 | E12: =SUM(B12:D12)
A13: Remb. NACRE | B13: 0 | C13: =F6*12 | D13: =F6*12 | E13: =SUM(B13:D13)
A14: TOTAL REMBOURSEMENTS | B14: =SUM(B11:B13) | C14: =SUM(C11:C13) | D14: =SUM(D11:D13) | E14: =SUM(E11:E13)
A15: Dont interets (pret bancaire) | B15: 375 | C15: 625 | D15: 500 | E15: =SUM(B15:D15)
A17: RESUME REMBOURSEMENTS MENSUELS
A18: M1-M6 : aucun remboursement (differe)
A19: M7-M12 : 728 EUR/mois (I95 278 + bancaire 450)
A20: M13+ : 821 EUR/mois (+ NACRE 93)
